logtext/__init__.py
logtext/fire.py
logtext/glitch.py
logtext/matrix.py
logtext/pulse.py
logtext-1.0.0.dist-info/METADATA
logtext-1.0.0.dist-info/WHEEL
logtext-1.0.0.dist-info/top_level.txt
logtext-1.0.0.dist-info/RECORD
