Metadata-Version: 2.1
Name: logtext
Version: 1.0.0
Summary: Next-Gen Terminal Art Engine
Author: kuavait
License: MIT
Requires-Dist: skytext>=0.1.0
